CHANGES.txt
MANIFEST.in
README.md
requirements.txt
setup.py
docs/MIGRATIONS.txt
wheelcms_axle/__init__.py
wheelcms_axle/access.py
wheelcms_axle/actions.py
wheelcms_axle/admin.py
wheelcms_axle/base.py
wheelcms_axle/brainstorm.txt
wheelcms_axle/configuration.py
wheelcms_axle/content.py
wheelcms_axle/context_processors.py
wheelcms_axle/forms.py
wheelcms_axle/impexp.py
wheelcms_axle/main.py
wheelcms_axle/models.py
wheelcms_axle/node.py
wheelcms_axle/queries.py
wheelcms_axle/quicktest_urls.py
wheelcms_axle/registry.py
wheelcms_axle/robots.py
wheelcms_axle/search.py
wheelcms_axle/search_sites.py
wheelcms_axle/sitemaps.py
wheelcms_axle/spoke.py
wheelcms_axle/stopwords.py
wheelcms_axle/stracks.py
wheelcms_axle/templates.py
wheelcms_axle/themes.py
wheelcms_axle/toolbar.py
wheelcms_axle/translate.py
wheelcms_axle/urls.py
wheelcms_axle/userena_custom.py
wheelcms_axle/utils.py
wheelcms_axle.egg-info/PKG-INFO
wheelcms_axle.egg-info/SOURCES.txt
wheelcms_axle.egg-info/dependency_links.txt
wheelcms_axle.egg-info/namespace_packages.txt
wheelcms_axle.egg-info/not-zip-safe
wheelcms_axle.egg-info/requires.txt
wheelcms_axle.egg-info/top_level.txt
wheelcms_axle/locale/en/LC_MESSAGES/django.mo
wheelcms_axle/locale/en/LC_MESSAGES/django.po
wheelcms_axle/locale/nl/LC_MESSAGES/django.mo
wheelcms_axle/locale/nl/LC_MESSAGES/django.po
wheelcms_axle/management/__init__.py
wheelcms_axle/management/commands/__init__.py
wheelcms_axle/management/commands/export.py
wheelcms_axle/management/commands/import.py
wheelcms_axle/management/commands/init.py
wheelcms_axle/migrations/0001_initial.py
wheelcms_axle/migrations/0002_auto__add_field_wheelprofile_twitter__add_field_wheelprofile_google__a.py
wheelcms_axle/migrations/__init__.py
wheelcms_axle/registries/__init__.py
wheelcms_axle/registries/configuration.py
wheelcms_axle/registries/fragments.py
wheelcms_axle/settings/__init__.py
wheelcms_axle/settings/settings_tinymce.py
wheelcms_axle/settings/settings_userena.py
wheelcms_axle/settings/settings_versions.py
wheelcms_axle/static/css/wheel.css
wheelcms_axle/static/css/wheel3.css
wheelcms_axle/static/css/wheel_content.css
wheelcms_axle/static/css/upload/jquery.fileupload-ui.css
wheelcms_axle/static/images/favicon.ico
wheelcms_axle/static/images/logo-notext.png
