Metadata-Version: 1.1
Name: wheelcms-axle
Version: 0.9
Summary: WheelCMS core package
Home-page: http://github.com/wheelcms/wheelcms_axle
Author: Ivo van der Wijk
Author-email: wheelcms@in.m3r.nl
License: BSD
Platform: UNKNOWN
Classifier: Programming Language :: Python
